pymsh.py
pymsh-1.2.2.dist-info/METADATA
pymsh-1.2.2.dist-info/WHEEL
pymsh-1.2.2.dist-info/licenses/LICENSE.md
pymsh-1.2.2.dist-info/RECORD
