Metadata-Version: 2.4
Name: pymsh
Version: 1.2.2
Summary: The Python multiset hashing library
Project-URL: Homepage, https://github.com/cgshep/pymsh
Project-URL: Issues, https://github.com/cgshep/pymsh/issues
Author-email: Carlton Shepherd <carlton@linux.com>
License: MIT
License-File: LICENSE.md
Keywords: crypto,cryptography,hash,hashing,multi-set,multiset,security
Classifier: Development Status :: 4 - Beta
Classifier: Intended Audience :: Developers
Classifier: Intended Audience :: Science/Research
Classifier: License :: OSI Approved :: MIT License
Classifier: Operating System :: OS Independent
Classifier: Programming Language :: Python :: 3
Classifier: Topic :: Security :: Cryptography
Requires-Python: >=3.7
Provides-Extra: test
Requires-Dist: mypy; extra == 'test'
Requires-Dist: pytest; extra == 'test'
